otel_extensions/__init__.py
otel_extensions/py.typed
otel_extensions-1.1.0.dist-info/LICENSE
otel_extensions-1.1.0.dist-info/METADATA
otel_extensions-1.1.0.dist-info/WHEEL
otel_extensions-1.1.0.dist-info/top_level.txt
otel_extensions-1.1.0.dist-info/zip-safe
otel_extensions-1.1.0.dist-info/RECORD
