Metadata-Version: 2.1
Name: otel-extensions
Version: 1.1.0
Summary: Python extensions for OpenTelemetry
Maintainer-email: Joe Savage <joe.savage@gmail.com>
License: Apache-2.0
Project-URL: Homepage, https://github.com/s4v4g3/otel-extensions-python
Project-URL: Source, https://github.com/s4v4g3/otel-extensions-python
Project-URL: Tracker, https://github.com/s4v4g3/otel-extensions-python/issues
Keywords: otel,opentelemetry,debug
Platform: any
Classifier: Intended Audience :: Developers
Classifier: License :: OSI Approved :: Apache Software License
Classifier: Operating System :: OS Independent
Classifier: Programming Language :: Python :: 3
Classifier: Programming Language :: Python :: 3 :: Only
Classifier: Programming Language :: Python :: 3.8
Classifier: Programming Language :: Python :: 3.9
Classifier: Programming Language :: Python :: 3.10
Classifier: Programming Language :: Python :: 3.11
Classifier: Programming Language :: Python :: 3.12
Classifier: Programming Language :: Python :: 3.13
Classifier: Topic :: Software Development :: Libraries
Classifier: Topic :: Software Development :: Testing
Classifier: Topic :: Utilities
Requires-Python: >=3.8
License-File: LICENSE
Requires-Dist: opentelemetry-api
Requires-Dist: opentelemetry-sdk
